<?xml version="1.0" encoding="utf-8" ?>
<dwsync>
<file name="main.css" server="xteamx.businesscatalyst.com//x16/" local="131536817880368638" remote="131536827480000000" Dst="0" />
<file name="main.min.css" server="xteamx.businesscatalyst.com//x16/" local="131536817881539426" remote="131536827490000000" Dst="0" />
<file name="app.js" server="xteamx.businesscatalyst.com//x16/" local="131536786462577854" remote="131536834140000000" Dst="0" />
<file name="app.min.js" server="xteamx.businesscatalyst.com//x16/" local="131536831815923538" remote="131536834160000000" Dst="0" />
<file name="jquery.js" server="xteamx.businesscatalyst.com//x16/" local="131536786461357052" remote="131536834170000000" Dst="0" />
<file name="jquery.leanModal.min.js" server="xteamx.businesscatalyst.com//x16/" local="131536786461712271" remote="131536834180000000" Dst="0" />
<file name="jquery.min.js" server="xteamx.businesscatalyst.com//x16/" local="131536832116088998" remote="131536834190000000" Dst="0" />
<file name="underscore.js" server="xteamx.businesscatalyst.com//x16/" local="131536786462192604" remote="131536834200000000" Dst="0" />
<file name="underscore.min.js" server="xteamx.businesscatalyst.com//x16/" local="131536832368632735" remote="131536834210000000" Dst="0" />
</dwsync>